annochan/__init__.py
annochan/coco.py
annochan-0.1.0.dist-info/METADATA
annochan-0.1.0.dist-info/WHEEL
annochan-0.1.0.dist-info/entry_points.txt
annochan-0.1.0.dist-info/RECORD
