Metadata-Version: 2.1
Name: annochan
Version: 0.1.0
Summary: 
Author: yumizu
Requires-Python: >=3.8.1,<=3.12.0
Classifier: Programming Language :: Python :: 3
Classifier: Programming Language :: Python :: 3.9
Classifier: Programming Language :: Python :: 3.10
Classifier: Programming Language :: Python :: 3.11
Classifier: Programming Language :: Python :: 3.12
Requires-Dist: pydantic (>=2.4.2,<3.0.0)
